externkit-0.1.0.dist-info/METADATA
externkit-0.1.0.dist-info/WHEEL
externkit-0.1.0.dist-info/licenses/LICENSE
externkit/__init__.py
externkit/env.pyi
externkit/externkit.cpython-313-x86_64-linux-gnu.so
externkit/externkit.pyi
externkit/py.typed
externkit-0.1.0.dist-info/RECORD
